tuminski_hash/__init__.py
tuminski_hash/core.py
tuminski_hash-1.0.0.dist-info/METADATA
tuminski_hash-1.0.0.dist-info/WHEEL
tuminski_hash-1.0.0.dist-info/top_level.txt
tuminski_hash-1.0.0.dist-info/RECORD
