Metadata-Version: 2.4
Name: tuminski_hash
Version: 1.0.0
Summary: Sistema de hash irreversível personalizado e seguro
Author: Vilmar Tuminski
Classifier: Programming Language :: Python :: 3
Classifier: License :: OSI Approved :: MIT License
Classifier: Operating System :: OS Independent
Requires-Python: >=3.6
Dynamic: author
Dynamic: classifier
Dynamic: requires-python
Dynamic: summary
